monster_chat_server-1.0.1.data/scripts/mc_server_start
server_app/__init__.py
server_app/mc_server_start.py
server_app/server.py
server_app/common/__init__.py
server_app/common/decorators.py
server_app/common/exceptions.py
server_app/common/utils.py
server_app/common/variables.py
server_app/db/__init__.py
server_app/db/db_client.py
server_app/db/db_clients_online.py
server_app/db/db_connect.py
server_app/db/db_contacts.py
server_app/db/db_history.py
server_app/db/db_stat.py
server_app/db/server_storage.py
server_app/logs/__init__.py
server_app/logs/decorators.py
server_app/logs/server_log_config.py
server_app/views/__init__.py
server_app/views/server_gui.py
monster_chat_server-1.0.1.dist-info/METADATA
monster_chat_server-1.0.1.dist-info/WHEEL
monster_chat_server-1.0.1.dist-info/top_level.txt
monster_chat_server-1.0.1.dist-info/RECORD
